<?xml version="1.0" encoding="UTF-8"?>
<ROM> 
  <RomName>dot_kuntao</RomName> 
  <VersionName>DOT-N-v1.1-20171118-kuntao-OFFICIAL</VersionName> 
  <VersionNumber type="integer">20171118</VersionNumber> 
  <DirectUrl></DirectUrl> 
  <HttpUrl>https://sourceforge.net/projects/dotos-ota/files/kuntao</HttpUrl>
  <Android>7.1.2</Android> 
  <CheckMD5></CheckMD5> 
  <FileSize type="integer">541065216</FileSize> <Developer>Abhay Ruparel</Developer>
  <Changelog>
* Fixed theme
* QS Panel Tiles Color : Pixel Blue
* QS Panel Modifications
* Added ParanoidCamera
* No longer dark video recording using PA Camera
* Memory leak Optimisation
* Other minimal misc   
  </Changelog>
</ROM>
