<?xml version="1.0" encoding="UTF-8"?>
<ROM>
  <RomName>dot_lettuce</RomName>
  <VersionName>DOT-N-v1.2-20171230-lettuce-OFFICIAL.zip</VersionName>
  <VersionNumber type="integer">20171230</VersionNumber>
  <DirectUrl>https://sourceforge.net/projects/dotos-ota/files/lettuce/DOT-N-v1.2-20171230-lettuce-OFFICIAL.zip</DirectUrl>
  <HttpUrl>https://sourceforge.net/projects/dotos-ota/files/lettuce</HttpUrl>
  <Android>7.1.2</Android>
  <CheckMD5>897cfcfcc6001a0ff59e38722ab23dd6</CheckMD5>
  <FileSize type="integer">451258518</FileSize>
  <Developer>Abhinav Gupta(agrd1129)</Developer>
  <Changelog>
  ** dotOS Changelog**
  -------------------
    Droid On Time!

    HAPPY NEW YEAR 
  
    device specific
    * add pa camera
    * used clang TC
    * bcleaned and reset all repos for more efficiency
    * more supportive audio
    * tweaks for latest security patch
  </Changelog>
</ROM>
