<?xml version="1.0" encoding="UTF-8"?>
<ROM>
  <RomName>dot_oneplus3</RomName>
  <VersionName>dotOS-O-v2.3-oneplus3-OFFICIAL-20180610</VersionName>
  <VersionNumber type="integer">20180610</VersionNumber>
  <DirectUrl>https://downloads.droidontime.com/oneplus3/dotOS-O-v2.3-oneplus3-OFFICIAL-20180610.zip</DirectUrl>
  <HttpUrl>https://downloads.droidontime.com/oneplus3</HttpUrl>
  <Android>8.1.0</Android>
  <CheckMD5>2a5194854c1d365ef832e07004d135c1</CheckMD5>
  <FileSize type="integer">521484467</FileSize>
  <Changelog>
    *Check dotOS telegram channel for weekly changelogs.
  </Changelog>
</ROM>
